pyallpay
