Metadata-Version: 1.1
Name: pyallpay
Version: 0.0.12.dev0
Summary: allPay API in python
Home-page: https://github.com/lockys/allpay.py
Author: Calvin Jeng
Author-email: lock4567@gmail.com
License: LICENSE
Platform: UNKNOWN
Classifier: Development Status :: 4 - Beta
Classifier: Environment :: Web Environment
Classifier: Intended Audience :: Developers
Classifier: License :: OSI Approved :: MIT License
Classifier: Operating System :: MacOS :: MacOS X
Classifier: Operating System :: Microsoft :: Windows
Classifier: Programming Language :: Python
Classifier: Topic :: Utilities
Classifier: Topic :: Software Development :: Libraries :: Python Modules
